<annotation>
  <folder>Person</folder>
  <filename>6111cd5ac1a4d0b3.jpg</filename>
  <path>C:\Users\Dell\Desktop\Dataset\train\Person\6111cd5ac1a4d0b3.jpg</path>
  <source>
    <database>Unknown</database>
  </source>
  <size>
    <width>683</width>
    <height>1024</height>
    <depth>3</depth>
  </size>
  <segmented>0</segmented>
  <object>
    <name>Person</name>
    <pose>Unspecified</pose>
    <truncated>0</truncated>
    <difficult>0</difficult>
    <bndbox>
      <xmin>145</xmin>
      <ymin>72</ymin>
      <xmax>666</xmax>
      <ymax>952</ymax>
    </bndbox>
  </object>
  <object>
    <name>Person</name>
    <pose>Unspecified</pose>
    <truncated>0</truncated>
    <difficult>0</difficult>
    <bndbox>
      <xmin>604</xmin>
      <ymin>0</ymin>
      <xmax>682</xmax>
      <ymax>314</ymax>
    </bndbox>
  </object>
</annotation>
