<annotation>
  <folder>Person</folder>
  <filename>ad296ac1c561356f.jpg</filename>
  <path>C:\Users\Dell\Desktop\Dataset\train\Person\ad296ac1c561356f.jpg</path>
  <source>
    <database>Unknown</database>
  </source>
  <size>
    <width>1024</width>
    <height>768</height>
    <depth>3</depth>
  </size>
  <segmented>0</segmented>
  <object>
    <name>Person</name>
    <pose>Unspecified</pose>
    <truncated>0</truncated>
    <difficult>0</difficult>
    <bndbox>
      <xmin>347</xmin>
      <ymin>271</ymin>
      <xmax>490</xmax>
      <ymax>733</ymax>
    </bndbox>
  </object>
  <object>
    <name>Person</name>
    <pose>Unspecified</pose>
    <truncated>0</truncated>
    <difficult>0</difficult>
    <bndbox>
      <xmin>432</xmin>
      <ymin>270</ymin>
      <xmax>550</xmax>
      <ymax>493</ymax>
    </bndbox>
  </object>
  <object>
    <name>Person</name>
    <pose>Unspecified</pose>
    <truncated>0</truncated>
    <difficult>0</difficult>
    <bndbox>
      <xmin>907</xmin>
      <ymin>213</ymin>
      <xmax>938</xmax>
      <ymax>323</ymax>
    </bndbox>
  </object>
</annotation>
