<annotation>
  <folder>Ball</folder>
  <filename>1780053331b9238e.jpg</filename>
  <path>C:\Users\Dell\Desktop\Dataset\train\Ball\1780053331b9238e.jpg</path>
  <source>
    <database>Unknown</database>
  </source>
  <size>
    <width>1024</width>
    <height>683</height>
    <depth>3</depth>
  </size>
  <segmented>0</segmented>
  <object>
    <name>Ball</name>
    <pose>Unspecified</pose>
    <truncated>0</truncated>
    <difficult>0</difficult>
    <bndbox>
      <xmin>357</xmin>
      <ymin>483</ymin>
      <xmax>388</xmax>
      <ymax>521</ymax>
    </bndbox>
  </object>
  <object>
    <name>Ball</name>
    <pose>Unspecified</pose>
    <truncated>0</truncated>
    <difficult>0</difficult>
    <bndbox>
      <xmin>655</xmin>
      <ymin>369</ymin>
      <xmax>676</xmax>
      <ymax>391</ymax>
    </bndbox>
  </object>
  <object>
    <name>Ball</name>
    <pose>Unspecified</pose>
    <truncated>0</truncated>
    <difficult>0</difficult>
    <bndbox>
      <xmin>713</xmin>
      <ymin>561</ymin>
      <xmax>753</xmax>
      <ymax>602</ymax>
    </bndbox>
  </object>
  <object>
    <name>Ball</name>
    <pose>Unspecified</pose>
    <truncated>0</truncated>
    <difficult>0</difficult>
    <bndbox>
      <xmin>793</xmin>
      <ymin>561</ymin>
      <xmax>833</xmax>
      <ymax>591</ymax>
    </bndbox>
  </object>
  <object>
    <name>Ball</name>
    <pose>Unspecified</pose>
    <truncated>0</truncated>
    <difficult>0</difficult>
    <bndbox>
      <xmin>898</xmin>
      <ymin>537</ymin>
      <xmax>934</xmax>
      <ymax>561</ymax>
    </bndbox>
  </object>
  <object>
    <name>Ball</name>
    <pose>Unspecified</pose>
    <truncated>0</truncated>
    <difficult>0</difficult>
    <bndbox>
      <xmin>983</xmin>
      <ymin>327</ymin>
      <xmax>996</xmax>
      <ymax>344</ymax>
    </bndbox>
  </object>
</annotation>
