<annotation>
  <folder>Ball</folder>
  <filename>7981870766e67144.jpg</filename>
  <path>C:\Users\Dell\Desktop\Dataset\train\Ball\7981870766e67144.jpg</path>
  <source>
    <database>Unknown</database>
  </source>
  <size>
    <width>1024</width>
    <height>685</height>
    <depth>3</depth>
  </size>
  <segmented>0</segmented>
  <object>
    <name>Ball</name>
    <pose>Unspecified</pose>
    <truncated>0</truncated>
    <difficult>0</difficult>
    <bndbox>
      <xmin>376</xmin>
      <ymin>201</ymin>
      <xmax>402</xmax>
      <ymax>227</ymax>
    </bndbox>
  </object>
</annotation>
