<annotation>
  <folder>Ball</folder>
  <filename>7e7669f60226db7a.jpg</filename>
  <path>C:\Users\Dell\Desktop\Dataset\train\Ball\7e7669f60226db7a.jpg</path>
  <source>
    <database>Unknown</database>
  </source>
  <size>
    <width>682</width>
    <height>1024</height>
    <depth>3</depth>
  </size>
  <segmented>0</segmented>
  <object>
    <name>Ball</name>
    <pose>Unspecified</pose>
    <truncated>0</truncated>
    <difficult>0</difficult>
    <bndbox>
      <xmin>148</xmin>
      <ymin>169</ymin>
      <xmax>193</xmax>
      <ymax>220</ymax>
    </bndbox>
  </object>
</annotation>
