<annotation>
  <folder>Ball</folder>
  <filename>ca54c5e6943aba23.jpg</filename>
  <path>C:\Users\Dell\Desktop\Dataset\train\Ball\ca54c5e6943aba23.jpg</path>
  <source>
    <database>Unknown</database>
  </source>
  <size>
    <width>980</width>
    <height>768</height>
    <depth>3</depth>
  </size>
  <segmented>0</segmented>
  <object>
    <name>Ball</name>
    <pose>Unspecified</pose>
    <truncated>0</truncated>
    <difficult>0</difficult>
    <bndbox>
      <xmin>255</xmin>
      <ymin>614</ymin>
      <xmax>350</xmax>
      <ymax>712</ymax>
    </bndbox>
  </object>
</annotation>
