<annotation>
  <folder>Footwear</folder>
  <filename>2049de023a57f3a7.jpg</filename>
  <path>C:\Users\Dell\Desktop\Dataset\train\Footwear\2049de023a57f3a7.jpg</path>
  <source>
    <database>Unknown</database>
  </source>
  <size>
    <width>1024</width>
    <height>686</height>
    <depth>3</depth>
  </size>
  <segmented>0</segmented>
  <object>
    <name>Footwear</name>
    <pose>Unspecified</pose>
    <truncated>0</truncated>
    <difficult>0</difficult>
    <bndbox>
      <xmin>501</xmin>
      <ymin>654</ymin>
      <xmax>522</xmax>
      <ymax>674</ymax>
    </bndbox>
  </object>
  <object>
    <name>Footwear</name>
    <pose>Unspecified</pose>
    <truncated>0</truncated>
    <difficult>0</difficult>
    <bndbox>
      <xmin>514</xmin>
      <ymin>662</ymin>
      <xmax>541</xmax>
      <ymax>685</ymax>
    </bndbox>
  </object>
  <object>
    <name>Footwear</name>
    <pose>Unspecified</pose>
    <truncated>0</truncated>
    <difficult>0</difficult>
    <bndbox>
      <xmin>635</xmin>
      <ymin>671</ymin>
      <xmax>680</xmax>
      <ymax>685</ymax>
    </bndbox>
  </object>
  <object>
    <name>Footwear</name>
    <pose>Unspecified</pose>
    <truncated>0</truncated>
    <difficult>0</difficult>
    <bndbox>
      <xmin>865</xmin>
      <ymin>263</ymin>
      <xmax>875</xmax>
      <ymax>277</ymax>
    </bndbox>
  </object>
  <object>
    <name>Footwear</name>
    <pose>Unspecified</pose>
    <truncated>0</truncated>
    <difficult>0</difficult>
    <bndbox>
      <xmin>946</xmin>
      <ymin>435</ymin>
      <xmax>988</xmax>
      <ymax>455</ymax>
    </bndbox>
  </object>
  <object>
    <name>Footwear</name>
    <pose>Unspecified</pose>
    <truncated>0</truncated>
    <difficult>0</difficult>
    <bndbox>
      <xmin>970</xmin>
      <ymin>414</ymin>
      <xmax>989</xmax>
      <ymax>440</ymax>
    </bndbox>
  </object>
</annotation>
