<annotation>
  <folder>Footwear</folder>
  <filename>7ef643d4667fa51c.jpg</filename>
  <path>C:\Users\Dell\Desktop\Dataset\train\Footwear\7ef643d4667fa51c.jpg</path>
  <source>
    <database>Unknown</database>
  </source>
  <size>
    <width>683</width>
    <height>1024</height>
    <depth>3</depth>
  </size>
  <segmented>0</segmented>
  <object>
    <name>Footwear</name>
    <pose>Unspecified</pose>
    <truncated>0</truncated>
    <difficult>0</difficult>
    <bndbox>
      <xmin>380</xmin>
      <ymin>854</ymin>
      <xmax>419</xmax>
      <ymax>914</ymax>
    </bndbox>
  </object>
  <object>
    <name>Footwear</name>
    <pose>Unspecified</pose>
    <truncated>0</truncated>
    <difficult>0</difficult>
    <bndbox>
      <xmin>458</xmin>
      <ymin>695</ymin>
      <xmax>512</xmax>
      <ymax>836</ymax>
    </bndbox>
  </object>
</annotation>
