<annotation>
  <folder>Footwear</folder>
  <filename>83378a3b35f135dc.jpg</filename>
  <path>C:\Users\Dell\Desktop\Dataset\train\Footwear\83378a3b35f135dc.jpg</path>
  <source>
    <database>Unknown</database>
  </source>
  <size>
    <width>768</width>
    <height>1024</height>
    <depth>3</depth>
  </size>
  <segmented>0</segmented>
  <object>
    <name>Footwear</name>
    <pose>Unspecified</pose>
    <truncated>0</truncated>
    <difficult>0</difficult>
    <bndbox>
      <xmin>168</xmin>
      <ymin>972</ymin>
      <xmax>195</xmax>
      <ymax>979</ymax>
    </bndbox>
  </object>
  <object>
    <name>Footwear</name>
    <pose>Unspecified</pose>
    <truncated>0</truncated>
    <difficult>0</difficult>
    <bndbox>
      <xmin>193</xmin>
      <ymin>975</ymin>
      <xmax>257</xmax>
      <ymax>993</ymax>
    </bndbox>
  </object>
</annotation>
