<annotation>
  <folder>Footwear</folder>
  <filename>fee666e1c7a33fdd.jpg</filename>
  <path>C:\Users\Dell\Desktop\Dataset\train\Footwear\fee666e1c7a33fdd.jpg</path>
  <source>
    <database>Unknown</database>
  </source>
  <size>
    <width>1024</width>
    <height>1024</height>
    <depth>3</depth>
  </size>
  <segmented>0</segmented>
  <object>
    <name>Footwear</name>
    <pose>Unspecified</pose>
    <truncated>0</truncated>
    <difficult>0</difficult>
    <bndbox>
      <xmin>132</xmin>
      <ymin>805</ymin>
      <xmax>188</xmax>
      <ymax>843</ymax>
    </bndbox>
  </object>
  <object>
    <name>Footwear</name>
    <pose>Unspecified</pose>
    <truncated>0</truncated>
    <difficult>0</difficult>
    <bndbox>
      <xmin>181</xmin>
      <ymin>820</ymin>
      <xmax>232</xmax>
      <ymax>850</ymax>
    </bndbox>
  </object>
</annotation>
